argument_parsing/__init__.py
argument_parsing-1.0.1.dist-info/LICENSE
argument_parsing-1.0.1.dist-info/METADATA
argument_parsing-1.0.1.dist-info/WHEEL
argument_parsing-1.0.1.dist-info/top_level.txt
argument_parsing-1.0.1.dist-info/RECORD
