Metadata-Version: 2.1
Name: argument_parsing
Version: 1.0.1
Summary: A zero dependency argument parser written in python.
Home-page: https://github.com/flpeters/argument_parsing
Download-URL: https://github.com/flpeters/argument_parsing
Author: Florian Peters
License: GNU General Public License v2 (GPLv2)
Project-URL: Source Code, https://github.com/flpeters/argument_parsing
Project-URL: Documentation, https://github.com/flpeters/argument_parsing
Project-URL: Bug Tracker, https://github.com/flpeters/argument_parsing/issues
Classifier: License :: OSI Approved :: GNU General Public License v2 (GPLv2)
Classifier: Programming Language :: Python
Classifier: Programming Language :: Python :: 3
Classifier: Programming Language :: Python :: 3 :: Only
Classifier: Programming Language :: Python :: 3.8
Classifier: Programming Language :: Python :: 3.9
Classifier: Programming Language :: Python :: 3.10
Classifier: Programming Language :: Python :: 3.11
Classifier: Programming Language :: Python :: 3.12
Classifier: Programming Language :: Python :: 3.13
Classifier: Development Status :: 3 - Alpha
Classifier: Intended Audience :: Developers
Requires-Python: >=3.8
License-File: LICENSE
